bvhsdk/__init__.py
bvhsdk/anim.py
bvhsdk/bvh.py
bvhsdk/egocentriccoord.py
bvhsdk/ik.py
bvhsdk/mathutils.py
bvhsdk/plotanimation.py
bvhsdk/retarget.py
bvhsdk/skeletonmap.py
bvhsdk/surface.py
bvhsdk/gui/__init__.py
bvhsdk/gui/main.py
bvhsdk-0.2.1.dist-info/LICENSE
bvhsdk-0.2.1.dist-info/WHEEL
bvhsdk-0.2.1.dist-info/METADATA
bvhsdk-0.2.1.dist-info/RECORD
